ptahlmud/__init__.py
ptahlmud/backtesting/__init__.py
ptahlmud/backtesting/backtest.py
ptahlmud/backtesting/models/__init__.py
ptahlmud/backtesting/models/barriers.py
ptahlmud/backtesting/models/signal.py
ptahlmud/backtesting/operations.py
ptahlmud/backtesting/portfolio.py
ptahlmud/backtesting/positions.py
ptahlmud/core/__init__.py
ptahlmud/core/fluctuations.py
ptahlmud/core/period.py
ptahlmud/datastack/__init__.py
ptahlmud/datastack/clients/__init__.py
ptahlmud/datastack/clients/binance_client.py
ptahlmud/datastack/clients/remote_client.py
ptahlmud/datastack/custom_operations.py
ptahlmud/datastack/fluctuations_repository.py
ptahlmud/datastack/fluctuations_service.py
ptahlmud/testing/__init__.py
ptahlmud/testing/fluctuations.py
ptahlmud-0.0.7.dist-info/LICENSE
ptahlmud-0.0.7.dist-info/METADATA
ptahlmud-0.0.7.dist-info/WHEEL
ptahlmud-0.0.7.dist-info/RECORD
