Metadata-Version: 2.3
Name: ptahlmud
Version: 0.0.7
Summary: Trading strategies crafting tools
Author: Baptiste Bouillon
Author-email: 1bouillonbaptiste@gmail.com
Requires-Python: >=3.11,<4.0
Classifier: Programming Language :: Python :: 3
Classifier: Programming Language :: Python :: 3.11
Classifier: Programming Language :: Python :: 3.12
Classifier: Programming Language :: Python :: 3.13
Requires-Dist: numpy (>=2.0,<3)
Requires-Dist: pandas (>=2.3.0,<3)
Requires-Dist: pydantic (>=2.11,<3)
Requires-Dist: python-binance (>=1.0.29,<2)
Requires-Dist: tqdm (>=4.67.1,<5.0.0)
Requires-Dist: types-tqdm (>=4.67.0.20250516,<5.0.0.0)
